setup.py
xpa_test/__init__.py
xpa_test/xpa_test.py
xpa_test.egg-info/PKG-INFO
xpa_test.egg-info/SOURCES.txt
xpa_test.egg-info/dependency_links.txt
xpa_test.egg-info/top_level.txt