Metadata-Version: 1.0
Name: xpa-test
Version: 0.0.4
Summary: get a test by random
Home-page: UNKNOWN
Author: xpa
Author-email: xupa123@163.com
License: MIT License
Platform: UNKNOWN
